extended_networkx_tools/Analytics.py
extended_networkx_tools/AnalyticsGraph.py
extended_networkx_tools/Creator.py
extended_networkx_tools/Printer.py
extended_networkx_tools/Solver.py
extended_networkx_tools/Tools.py
extended_networkx_tools/Visual.py
extended_networkx_tools/__init__.py
extended_networkx_tools-0.16.1rc1.dist-info/LICENSE
extended_networkx_tools-0.16.1rc1.dist-info/METADATA
extended_networkx_tools-0.16.1rc1.dist-info/WHEEL
extended_networkx_tools-0.16.1rc1.dist-info/top_level.txt
extended_networkx_tools-0.16.1rc1.dist-info/RECORD
