Metadata-Version: 2.1
Name: extended-networkx-tools
Version: 0.16.1rc1
Summary: Tools package for extending functionality of the networkx package.
Home-page: https://github.com/vonNiklasson/extended-networkx-tools
Author: Johan Niklasson, Oskar Hahr
Author-email: jnikl@kth.se, ohahr@kth.se
License: MIT
Keywords: graph,distributed average consensus,convergence rate,networkx
Platform: UNKNOWN
Classifier: Development Status :: 3 - Alpha
Classifier: Intended Audience :: Developers
Classifier: Intended Audience :: Science/Research
Classifier: Topic :: System :: Distributed Computing
Classifier: Topic :: Scientific/Engineering :: Mathematics
Classifier: License :: OSI Approved :: MIT License
Classifier: Programming Language :: Python :: 3.6
Classifier: Programming Language :: Python :: 3.7
Requires-Python: ~=3.6
Requires-Dist: cycler
Requires-Dist: decorator
Requires-Dist: kiwisolver
Requires-Dist: matplotlib
Requires-Dist: networkx
Requires-Dist: numpy
Requires-Dist: numba
Requires-Dist: pyparsing
Requires-Dist: python-dateutil
